{
    "key": "group_6706f23e55680",
    "title": "Office properties",
    "fields": [
        {
            "key": "field_67804f8d3dfac",
            "label": "Location",
            "name": "location",
            "aria-label": "",
            "type": "text",
            "instructions": "The name of the city or country the office is located in; displayed on some listing pages",
            "required": 0,
            "conditional_logic": 0,
            "wrapper": {
                "width": "",
                "class": "",
                "id": ""
            },
            "admin_column_enabled": 0,
            "default_value": "",
            "maxlength": "",
            "allow_in_bindings": 0,
            "placeholder": "City Name",
            "prepend": "",
            "append": ""
        },
        {
            "key": "field_670809ad04827",
            "label": "Email",
            "name": "email",
            "aria-label": "",
            "type": "email",
            "instructions": "",
            "required": 0,
            "conditional_logic": 0,
            "wrapper": {
                "width": "",
                "class": "",
                "id": ""
            },
            "admin_column_enabled": 1,
            "admin_column_position": "",
            "admin_column_width": "",
            "default_value": "",
            "allow_in_bindings": 0,
            "placeholder": "contact-our-office@cumming-group.com",
            "prepend": "",
            "append": ""
        },
        {
            "key": "field_670809d304828",
            "label": "Phone",
            "name": "phone",
            "aria-label": "",
            "type": "text",
            "instructions": "",
            "required": 0,
            "conditional_logic": 0,
            "wrapper": {
                "width": "",
                "class": "",
                "id": ""
            },
            "admin_column_enabled": 1,
            "admin_column_position": "",
            "admin_column_width": "",
            "default_value": "",
            "maxlength": "",
            "allow_in_bindings": 0,
            "placeholder": "555-555-1212",
            "prepend": "",
            "append": ""
        },
        {
            "key": "field_670809e404829",
            "label": "Address",
            "name": "address",
            "aria-label": "",
            "type": "textarea",
            "instructions": "",
            "required": 0,
            "conditional_logic": 0,
            "wrapper": {
                "width": "",
                "class": "",
                "id": ""
            },
            "admin_column_enabled": 0,
            "default_value": "",
            "maxlength": "",
            "allow_in_bindings": 0,
            "rows": 3,
            "placeholder": "",
            "new_lines": "wpautop"
        }
    ],
    "location": [
        [
            {
                "param": "post_type",
                "operator": "==",
                "value": "office"
            }
        ]
    ],
    "menu_order": -1,
    "position": "side",
    "style": "default",
    "label_placement": "top",
    "instruction_placement": "label",
    "hide_on_screen": "",
    "active": true,
    "description": "",
    "show_in_rest": 0,
    "modified": 1736462581
}
