{
    "key": "group_678868eddf976",
    "title": "Team List Block",
    "fields": [
        {
            "key": "field_678868eeb1c4b",
            "label": "Team members",
            "name": "posts",
            "aria-label": "",
            "type": "relationship",
            "instructions": "",
            "required": 0,
            "conditional_logic": 0,
            "wrapper": {
                "width": "",
                "class": "",
                "id": ""
            },
            "admin_column_enabled": 0,
            "post_type": [
                "person"
            ],
            "post_status": [
                "publish"
            ],
            "taxonomy": "",
            "filters": [
                "search"
            ],
            "return_format": "id",
            "min": "",
            "max": "",
            "allow_in_bindings": 0,
            "elements": "",
            "bidirectional": 0,
            "bidirectional_target": []
        }
    ],
    "location": [
        [
            {
                "param": "block",
                "operator": "==",
                "value": "acf\/cg-list-team"
            }
        ]
    ],
    "menu_order": 0,
    "position": "normal",
    "style": "default",
    "label_placement": "top",
    "instruction_placement": "label",
    "hide_on_screen": "",
    "active": true,
    "description": "",
    "show_in_rest": 0,
    "modified": 1737054539
}
